fastsemsim/__init__.py
fastsemsim/fastsemsim_cmdline.py
fastsemsim/version
fastsemsim/ac/AnnotationCorpus.py
fastsemsim/ac/GAF2AnnotationCorpusParser.py
fastsemsim/ac/NCBIAnnotationCorpusParser.py
fastsemsim/ac/PlainAnnotationCorpusParser.py
fastsemsim/ac/__init__.py
fastsemsim/ac/_libs.py
fastsemsim/ac/toremove_GOAnnotationCorpus.py
fastsemsim/api/BatchSemSim.py
fastsemsim/api/__init__.py
fastsemsim/data/Dataset.py
fastsemsim/data/__init__.py
fastsemsim/data/dataset.txt
fastsemsim/data/ACs/DO_human_Osborne_BMC_2010.08.24.txt
fastsemsim/data/ACs/DO_human_Peng_NAR_2014.10.12.txt
fastsemsim/data/ACs/GO.goa_arabidopsis_2019.01.29.gz
fastsemsim/data/ACs/GO.goa_fly_2019.01.29.gz
fastsemsim/data/ACs/GO.goa_human_2019.01.29.gz
fastsemsim/data/ACs/GO.goa_mouse_2019.01.29.gz
fastsemsim/data/ACs/GO.goa_rat_2019.01.29.gz
fastsemsim/data/ACs/GO.goa_worm_2019.01.29.gz
fastsemsim/data/ACs/GO.goa_zebrafish_2019.01.29.gz
fastsemsim/data/Os/CellOntology_2014.10.13.obo
fastsemsim/data/Os/CellOntology_2019.01.29.obo
fastsemsim/data/Os/DiseaseOntology_2014.10.13.obo
fastsemsim/data/Os/DiseaseOntology_2019.01.29.obo
fastsemsim/data/Os/DiseaseOntology_2019.03.07.obo
fastsemsim/data/Os/GeneOntology_2019.01.29.obo
fastsemsim/data/Os/GeneOntology_2019.01.29.obo-xml.gz
fastsemsim/data/Os/HumanPhenotypeOntology_2019.01.29.obo
fastsemsim/data/Os/pato_2014.09.09.obo
fastsemsim/data/__pycache__/Dataset.cpython-35.pyc
fastsemsim/data/__pycache__/__init__.cpython-35.pyc
fastsemsim/data/input_dataset_processing/DOA.sh
fastsemsim/data/input_dataset_processing/GOA.sh
fastsemsim/data/input_dataset_processing/Os.sh
fastsemsim/examples/.A.swp
fastsemsim/examples/.B.swp
fastsemsim/examples/README
fastsemsim/examples/__init__.py
fastsemsim/examples/calculate_ss_on_go.py
fastsemsim/examples/example_cmdline.sh
fastsemsim/examples/example_cmdline_params.txt
fastsemsim/examples/load_annotation_corpus.py
fastsemsim/examples/load_go_annotation_corpus.py
fastsemsim/examples/load_ontology.py
fastsemsim-1.0.0.dist-info/LICENSE
fastsemsim-1.0.0.dist-info/METADATA
fastsemsim-1.0.0.dist-info/WHEEL
fastsemsim-1.0.0.dist-info/entry_points.txt
fastsemsim-1.0.0.dist-info/top_level.txt
fastsemsim-1.0.0.dist-info/RECORD
