Metadata-Version: 2.1
Name: fastsemsim
Version: 1.0.0
Summary: FastSemSim is a Python package to calculate semantic similarity over ontologies (including the Gene Ontology).
Requires-Dist: pandas
